amazon_order_history_to_transactions/__init__.py
amazon_order_history_to_transactions/config.py
amazon_order_history_to_transactions/data_processor.py
amazon_order_history_to_transactions/main.py
amazon_order_history_to_transactions-0.1.1.dist-info/METADATA
amazon_order_history_to_transactions-0.1.1.dist-info/WHEEL
amazon_order_history_to_transactions-0.1.1.dist-info/entry_points.txt
amazon_order_history_to_transactions-0.1.1.dist-info/licenses/LICENSE.md
amazon_order_history_to_transactions-0.1.1.dist-info/RECORD
