Metadata-Version: 2.4
Name: amazon-order-history-to-transactions
Version: 0.1.1
Summary: Convert Amazon order history to credit card-like transactions
Project-URL: Homepage, https://github.com/holocronweaver/amazon-order-history-to-transactions
Project-URL: Repository, https://github.com/holocronweaver/amazon-order-history-to-transactions.git
Project-URL: Issues, https://github.com/holocronweaver/amazon-order-history-to-transactions/issues
Author-email: Jesse Johnson <1024369+holocronweaver@users.noreply.github.com>
Maintainer-email: Jesse Johnson <1024369+holocronweaver@users.noreply.github.com>
License: # GNU GENERAL PUBLIC LICENSE
License-File: LICENSE.md
Keywords: amazon,csv,finance,order-history,transaction
Classifier: Development Status :: 4 - Beta
Classifier: Intended Audience :: End Users/Desktop
Classifier: License :: OSI Approved :: GNU General Public License v3 (GPLv3)
Classifier: Operating System :: OS Independent
Classifier: Programming Language :: Python :: 3
Classifier: Programming Language :: Python :: 3.9
Classifier: Programming Language :: Python :: 3.10
Classifier: Programming Language :: Python :: 3.11
Classifier: Programming Language :: Python :: 3.12
Classifier: Topic :: Office/Business :: Financial
Classifier: Topic :: Utilities
Requires-Python: >=3.9
Requires-Dist: pandas>=2.0.0
Provides-Extra: test
Requires-Dist: pytest>=7.0.0; extra == 'test'
